PySender/__init__.py
PySender/__main__.py
PySender/__version__.py
PySender/dialogs.py
PySender/errors.py
PySender/request.py
PySender/res/icon.png
PySender/ui/about.py
PySender/ui/ui.py
PySender-2.4.1.dist-info/LICENSE
PySender-2.4.1.dist-info/METADATA
PySender-2.4.1.dist-info/WHEEL
PySender-2.4.1.dist-info/entry_points.txt
PySender-2.4.1.dist-info/top_level.txt
PySender-2.4.1.dist-info/RECORD
