Metadata-Version: 2.1
Name: PySender
Version: 2.4.1
Summary: PyQt app to send REST API requests
Home-page: https://github.com/fast-geek/PySender
Author: lavender
Author-email: support@lavender.ml
License: MIT
Project-URL: Homepage, https://github.com/fast-geek/PySender
Project-URL: Donate, https://lavtg.ml/donat
Keywords: python pyqt rest api
Platform: UNKNOWN
Classifier: Programming Language :: Python :: 3
Classifier: Development Status :: 4 - Beta
Classifier: License :: OSI Approved :: MIT License
Classifier: Operating System :: OS Independent
Requires-Python: >=3.6.1
Requires-Dist: PyQt5
Requires-Dist: requests
